nuitkabs/__init__.py
nuitkabs/nbuilder.py
nuitkabs/yaml_compat.py
nuitkabs/builders/__init__.py
nuitkabs/builders/arg_processor.py
nuitkabs/builders/executable.py
nuitkabs/builders/generic.py
nuitkabs/builders/module.py
nuitkabs/builders/package_finder.py
nuitkabs-0.0.2.dist-info/LICENSE
nuitkabs-0.0.2.dist-info/METADATA
nuitkabs-0.0.2.dist-info/WHEEL
nuitkabs-0.0.2.dist-info/entry_points.txt
nuitkabs-0.0.2.dist-info/top_level.txt
nuitkabs-0.0.2.dist-info/RECORD
